[
  {
    "מדד": "תיקופים שבועיים Q2/25",
    "נתונים במאגר": "10,846,861",
    "סך הכל בענף": "19,000,000",
    "אחוז מהענף": "57.09%"
  },
  {
    "מדד": "גידול מ-2018 בתיקופים",
    "נתונים במאגר": "20.10%",
    "סך הכל בענף": "11.76%",
    "אחוז מהענף": ""
  },
  {
    "מדד": "קווים פעילים Q2/25",
    "נתונים במאגר": "780",
    "סך הכל בענף": "2900",
    "אחוז מהענף": "26.90%"
  },
  {
    "מדד": "קווים לא פעילים",
    "נתונים במאגר": "155",
    "סך הכל בענף": "",
    "אחוז מהענף": ""
  },
  {
    "מדד": "המערכת מתמקדת בקווים חזקים יחסית ברשת, ולכן נוצר פער בו המערכת מציגה  רק כרבע מהקווים ברשת עם כ-60% מהנסיעות",
    "נתונים במאגר": "",
    "סך הכל בענף": "",
    "אחוז מהענף": ""
  },
  {
    "מדד": "המערכת מתמקדת בקבוצות קווים שעברו שינויים גדולים ולכן נוצר פער בו המערכת מציגה גידול של 20% בתיקופים לעומת 11.75% בלבד בכלל ארצי",
    "נתונים במאגר": "",
    "סך הכל בענף": "",
    "אחוז מהענף": ""
  }
]
